asta_summarizer/__init__.py
asta_summarizer/service.py
asta_summarizer/utils.py
asta_summarizer/models/SummarizationType.py
asta_summarizer/prompts/main_prompt.txt
asta_summarizer/prompts/summary_type_prompts.py
asta_summarizer-0.1.1.dist-info/licenses/LICENSE
asta_summarizer-0.1.1.dist-info/METADATA
asta_summarizer-0.1.1.dist-info/WHEEL
asta_summarizer-0.1.1.dist-info/top_level.txt
asta_summarizer-0.1.1.dist-info/RECORD
